[
    {
        "key": "dbln",
        "value": "%7B%2261563138265655%22%3A%22UjLm5cfL%22%7D",
        "domain": "facebook.com",
        "path": "/login/device-based/",
        "hostOnly": false,
        "creation": "2025-05-05T09:39:26.479Z",
        "lastAccessed": "2025-05-05T09:39:26.479Z"
    },
    {
        "key": "datr",
        "value": "l4gYaDrF3WMpP1YpawYyDLVP",
        "domain": "facebook.com",
        "path": "/",
        "hostOnly": false,
        "creation": "2025-05-05T09:39:26.479Z",
        "lastAccessed": "2025-05-05T09:39:26.479Z"
    },
    {
        "key": "sb",
        "value": "l4gYaH_FKLBG36yaRkT1WqDC",
        "domain": "facebook.com",
        "path": "/",
        "hostOnly": false,
        "creation": "2025-05-05T09:39:26.479Z",
        "lastAccessed": "2025-05-05T09:39:26.479Z"
    },
    {
        "key": "m_pixel_ratio",
        "value": "2",
        "domain": "facebook.com",
        "path": "/",
        "hostOnly": false,
        "creation": "2025-05-05T09:39:26.479Z",
        "lastAccessed": "2025-05-05T09:39:26.479Z"
    },
    {
        "key": "wd",
        "value": "360x640",
        "domain": "facebook.com",
        "path": "/",
        "hostOnly": false,
        "creation": "2025-05-05T09:39:26.479Z",
        "lastAccessed": "2025-05-05T09:39:26.479Z"
    },
    {
        "key": "c_user",
        "value": "61563138265655",
        "domain": "facebook.com",
        "path": "/",
        "hostOnly": false,
        "creation": "2025-05-05T09:39:26.479Z",
        "lastAccessed": "2025-05-05T09:39:26.479Z"
    },
    {
        "key": "fr",
        "value": "0KbaNU3WrKAhGHNZG.AWdrWmlo-_wJyNUiaYDb5casLaK8ooGQ5p5tX7TeP1Xxe3kDQ4Y.BoGIiX..AAA.0.0.BoGImw.AWdx16E7FJvmsfMGgPDDyA4hx-U",
        "domain": "facebook.com",
        "path": "/",
        "hostOnly": false,
        "creation": "2025-05-05T09:39:26.479Z",
        "lastAccessed": "2025-05-05T09:39:26.479Z"
    },
    {
        "key": "xs",
        "value": "5%3A2oa1_Z9WbCePdA%3A2%3A1746438583%3A-1%3A5903",
        "domain": "facebook.com",
        "path": "/",
        "hostOnly": false,
        "creation": "2025-05-05T09:39:26.479Z",
        "lastAccessed": "2025-05-05T09:39:26.479Z"
    },
    {
        "key": "locale",
        "value": "en_GB",
        "domain": "facebook.com",
        "path": "/",
        "hostOnly": false,
        "creation": "2025-05-05T09:39:26.479Z",
        "lastAccessed": "2025-05-05T09:39:26.479Z"
    },
    {
        "key": "wl_cbv",
        "value": "v2%3Bclient_version%3A2805%3Btimestamp%3A1746438590",
        "domain": "facebook.com",
        "path": "/",
        "hostOnly": false,
        "creation": "2025-05-05T09:39:26.479Z",
        "lastAccessed": "2025-05-05T09:39:26.479Z"
    },
    {
        "key": "fbl_st",
        "value": "100738069%3BT%3A29107297",
        "domain": "facebook.com",
        "path": "/",
        "hostOnly": false,
        "creation": "2025-05-05T09:39:26.479Z",
        "lastAccessed": "2025-05-05T09:39:26.479Z"
    },
    {
        "key": "vpd",
        "value": "v1%3B512x360x2",
        "domain": "facebook.com",
        "path": "/",
        "hostOnly": false,
        "creation": "2025-05-05T09:39:26.479Z",
        "lastAccessed": "2025-05-05T09:39:26.479Z"
    }
]
